common_tools/__init__.py
common_tools/common_tools.py
common_tools/auto_compression/__init__.py
common_tools/auto_compression/fd_auto_compress/__init__.py
common_tools/auto_compression/fd_auto_compress/dataset.py
common_tools/auto_compression/fd_auto_compress/fd_auto_compress.py
fastdeploy_tools-0.0.5.dist-info/METADATA
fastdeploy_tools-0.0.5.dist-info/WHEEL
fastdeploy_tools-0.0.5.dist-info/entry_points.txt
fastdeploy_tools-0.0.5.dist-info/top_level.txt
fastdeploy_tools-0.0.5.dist-info/RECORD
