Metadata-Version: 2.1
Name: fastdeploy-tools
Version: 0.0.5
Summary: A toolkit for FastDeploy.
License: Apache 2.0
Platform: UNKNOWN
Classifier: Programming Language :: Python :: 3
Classifier: License :: OSI Approved :: Apache Software License
Classifier: Operating System :: OS Independent
Requires-Dist: uvicorn (==0.16.0)
